{
  "colors": [
    [ 244, 78, 59 ],
    [ 251, 158, 0 ],
    [ 250, 40, 255 ],
    [ 104, 188, 0 ],
    [ 115, 216, 255 ]
  ],
  "background": "island-bg",
  "queues": [
    [
      [ 0, 3 ],
      [ 0, 3 ],
      [ 1, 3, 4 ],
      [ 0 ],
      [ 4, 2 ],
      [ 4, 2 ],
      [ 1 ],
      [ 1, 0, 3 ],
      [ 0, 3 ],
      [ 0, 3 ],
      [ 4, 2 ],
      [ 1 ],
      [ 1, 0, 3 ],
      [ 0, 3 ],
      [ 0, 3 ]
    ],
    [
      [ 3, 0, 1 ],
      [ 3, 0, 1 ],
      [ 4, 2 ],
      [ 1 ],
      [ 1, 0, 3 ],
      [ 4, 2 ],
      [ 1 ],
      [ 1, 0, 3 ],
      [ 3, 0, 1 ],
      [ 3, 0, 1 ],
      [ 4, 2 ],
      [ 1 ],
      [ 1, 0, 3 ],
      [ 3, 0, 1 ],
      [ 3, 0, 1 ]
    ],
    [
      [ 1, 3, 4 ],
      [ 0 ],
      [ 4, 2 ],
      [ 4, 2 ],
      [ 1 ],
      [ 1, 0, 3 ],
      [ 2 ],
      [ 3, 0 ],
      [ 4, 2 ],
      [ 1 ],
      [ 1, 0, 3 ],
      [ 0, 3 ],
      [ 1, 3, 4 ],
      [ 0 ],
      [ 4, 2 ]
    ],
    [
      [ 4, 2 ],
      [ 1 ],
      [ 1, 0, 3 ],
      [ 1, 3, 4 ],
      [ 0 ],
      [ 4, 2 ],
      [ 3 ],
      [ 4, 2, 0 ],
      [ 1, 3, 4 ],
      [ 0 ],
      [ 4, 2 ],
      [ 3, 0, 1 ],
      [ 1, 3, 4 ],
      [ 0 ],
      [ 4, 2 ]
    ],
    [
      [ 1, 3, 4 ],
      [ 0 ],
      [ 4, 2 ],
      [ 4, 2 ],
      [ 1 ],
      [ 1, 0, 3 ],
      [ 4, 3 ],
      [ 2, 3 ],
      [ 4, 2 ],
      [ 1 ],
      [ 1, 0, 3 ],
      [ 1, 3, 4 ],
      [ 0 ],
      [ 4, 2 ],
      [ 3, 1, 2 ]
    ]
  ],
  "timer": {
    "levelTime": 160,
    "canvasBaseTime": 10
  },
  "version": 1,
  "scoreThreshold": 6200
}
